{
  "project_info": {
    "project_number": "674823742475",
    "project_id": "flutter-firebase-1aba7",
    "storage_bucket": "flutter-firebase-1aba7.appspot.com"
  },
  "client": [
    {
      "client_info": {
        "mobilesdk_app_id": "1:674823742475:android:26bf32779685a51899530e",
        "android_client_info": {
          "package_name": "com.example.flutter_firebase"
        }
      },
      "oauth_client": [],
      "api_key": [
        {
          "current_key": "AIzaSyBvu8It0pjcsMqsMZBPPu2A_wHB2eL1iDA"
        }
      ],
      "services": {
        "appinvite_service": {
          "other_platform_oauth_client": []
        }
      }
    }
  ],
  "configuration_version": "1"
}